{
  "schema_version": "1.6",
  "fips": "08025",
  "name": "Crowley County",
  "state": "CO",
  "centroid": {
    "lat": 38.30618,
    "lon": -103.772736
  },
  "alerts": {
    "weather": [
      {
        "event": "Red Flag Warning",
        "headline": "Red Flag Warning issued June 11 at 1:37AM MDT until June 11 at 6:00PM MDT by NWS Pueblo CO",
        "severity": "Severe",
        "urgency": "Expected",
        "effective": "2026-06-11T01:37:00-06:00",
        "expires": "2026-06-11T17:45:00-06:00",
        "areaDesc": "Crowley County Including Ordway; Kiowa County Including Eads; Bent County Including Las Animas; Prowers County Including Lamar",
        "id": "urn:oid:2.49.0.1.840.0.1efce1cfb5256c5da1c54625e2bd326c392fb6c5.003.1",
        "source": "nws_alert"
      }
    ],
    "bank_robbery": [],
    "protest": [],
    "utility_outage": [],
    "transit_disruption": [],
    "wildfires": [],
    "transit": [],
    "amtrak": [],
    "aviation": [],
    "fema": [],
    "disease": []
  },
  "alert_count": 1,
  "date": "2026-06-11",
  "generated_at": "2026-06-11T19:00:00.678894+00:00"
}
