{
  "schema_version": "1.6",
  "fips": "12087",
  "name": "Monroe County",
  "state": "FL",
  "centroid": {
    "lat": 25.58612,
    "lon": -81.022603
  },
  "alerts": {
    "weather": [
      {
        "event": "Heavy Precipitation Forecast",
        "headline": "~1.0\" rain expected in next 24h",
        "severity": "Moderate",
        "source": "nws_forecast"
      }
    ],
    "bank_robbery": [],
    "protest": [],
    "utility_outage": [],
    "transit_disruption": [],
    "wildfires": [],
    "transit": [],
    "amtrak": [],
    "aviation": [],
    "fema": [],
    "disease": []
  },
  "alert_count": 1,
  "date": "2026-07-01",
  "generated_at": "2026-07-01T10:58:14.933484+00:00"
}
