{
  "schema_version": "1.6",
  "fips": "18167",
  "name": "Vigo County",
  "state": "IN",
  "centroid": {
    "lat": 39.430874,
    "lon": -87.390989
  },
  "alerts": {
    "weather": [
      {
        "event": "Flood Warning",
        "headline": "Flood Warning issued June 22 at 10:55PM EDT until June 23 at 5:00PM EDT by NWS Indianapolis IN",
        "severity": "Severe",
        "urgency": "Immediate",
        "effective": "2026-06-22T22:55:00-04:00",
        "expires": "2026-06-23T14:00:00-04:00",
        "areaDesc": "Clark, IL; Crawford, IL; Sullivan, IN; Vigo, IN",
        "id": "urn:oid:2.49.0.1.840.0.b990743ebd723ba4da2d95d1696f8f68bdf68296.004.1",
        "source": "nws_alert"
      }
    ],
    "bank_robbery": [],
    "protest": [],
    "utility_outage": [],
    "transit_disruption": [],
    "wildfires": [],
    "transit": [],
    "amtrak": [],
    "aviation": [],
    "fema": [],
    "disease": []
  },
  "alert_count": 1,
  "date": "2026-06-23",
  "generated_at": "2026-06-23T10:50:48.012654+00:00"
}
