{
  "schema_version": "1.6",
  "fips": "20099",
  "name": "Labette County",
  "state": "KS",
  "centroid": {
    "lat": 37.191468,
    "lon": -95.297473
  },
  "alerts": {
    "weather": [
      {
        "event": "Flood Warning",
        "headline": "Flood Warning issued June 27 at 2:03AM CDT until June 30 at 6:35AM CDT by NWS Wichita KS",
        "severity": "Severe",
        "urgency": "Immediate",
        "effective": "2026-06-27T02:03:00-05:00",
        "expires": "2026-06-27T14:15:00-05:00",
        "areaDesc": "Cherokee, KS; Labette, KS",
        "id": "urn:oid:2.49.0.1.840.0.da20953c1d25ce6ee205d6867cfc465c8196b5e9.001.1",
        "source": "nws_alert"
      },
      {
        "event": "Flood Warning",
        "headline": "Flood Warning issued June 27 at 2:03AM CDT until June 29 at 3:52PM CDT by NWS Wichita KS",
        "severity": "Severe",
        "urgency": "Immediate",
        "effective": "2026-06-27T02:03:00-05:00",
        "expires": "2026-06-27T14:15:00-05:00",
        "areaDesc": "Labette, KS; Neosho, KS",
        "id": "urn:oid:2.49.0.1.840.0.da20953c1d25ce6ee205d6867cfc465c8196b5e9.002.1",
        "source": "nws_alert"
      },
      {
        "event": "Flood Warning",
        "headline": "Flood Warning issued June 27 at 12:40AM CDT until June 27 at 9:45AM CDT by NWS Wichita KS",
        "severity": "Severe",
        "urgency": "Expected",
        "effective": "2026-06-27T00:40:00-05:00",
        "expires": "2026-06-27T09:45:00-05:00",
        "areaDesc": "Chautauqua, KS; Labette, KS; Montgomery, KS",
        "id": "urn:oid:2.49.0.1.840.0.2d2184fc465a1defcdd7dfa2cdc0d1f1e54a3039.001.1",
        "source": "nws_alert"
      }
    ],
    "bank_robbery": [],
    "protest": [],
    "utility_outage": [],
    "transit_disruption": [],
    "wildfires": [],
    "transit": [],
    "amtrak": [],
    "aviation": [],
    "fema": [],
    "disease": []
  },
  "alert_count": 3,
  "date": "2026-06-27",
  "generated_at": "2026-06-27T09:38:25.150231+00:00"
}
