{
  "schema_version": "1.6",
  "fips": "21183",
  "name": "Ohio County",
  "state": "KY",
  "centroid": {
    "lat": 37.477859,
    "lon": -86.844871
  },
  "alerts": {
    "weather": [
      {
        "event": "Flood Warning",
        "headline": "Flood Warning issued June 29 at 6:38AM CDT until July 1 at 2:06AM CDT by NWS Louisville KY",
        "severity": "Severe",
        "urgency": "Immediate",
        "effective": "2026-06-29T06:38:00-05:00",
        "expires": "2026-06-30T14:45:00-05:00",
        "areaDesc": "Ohio, KY",
        "id": "urn:oid:2.49.0.1.840.0.67c33189cfbeb395aec17808bb579400c6e74bdd.001.1",
        "source": "nws_alert"
      },
      {
        "event": "Flood Warning",
        "headline": "Flood Warning issued June 28 at 8:46PM CDT until July 1 at 1:00PM CDT by NWS Louisville KY",
        "severity": "Severe",
        "urgency": "Immediate",
        "effective": "2026-06-28T20:46:00-05:00",
        "expires": "2026-06-29T15:00:00-05:00",
        "areaDesc": "Butler, KY; Muhlenberg, KY; Ohio, KY",
        "id": "urn:oid:2.49.0.1.840.0.7ab1015138c35269bb95dfe41329cc00e7680991.001.1",
        "source": "nws_alert"
      }
    ],
    "bank_robbery": [],
    "protest": [],
    "utility_outage": [],
    "transit_disruption": [],
    "wildfires": [],
    "transit": [],
    "amtrak": [],
    "aviation": [],
    "fema": [],
    "disease": []
  },
  "alert_count": 2,
  "date": "2026-06-29",
  "generated_at": "2026-06-29T12:16:22.145733+00:00"
}
