{
  "schema_version": "1.6",
  "fips": "23003",
  "name": "Aroostook County",
  "state": "ME",
  "centroid": {
    "lat": 46.709193,
    "lon": -68.612409
  },
  "alerts": {
    "weather": [
      {
        "event": "Flash Flood Warning",
        "headline": "Flash Flood Warning issued June 12 at 1:06PM EDT until June 12 at 3:00PM EDT by NWS Caribou ME",
        "severity": "Severe",
        "urgency": "Immediate",
        "effective": "2026-06-12T13:06:00-04:00",
        "expires": "2026-06-12T15:00:00-04:00",
        "areaDesc": "Aroostook, ME; Piscataquis, ME",
        "id": "urn:oid:2.49.0.1.840.0.eda0d7a0d9bbb30beaa4b445c41e1e201138ea1e.001.1",
        "source": "nws_alert"
      },
      {
        "event": "Flash Flood Warning",
        "headline": "Flash Flood Warning issued June 12 at 12:44PM EDT until June 12 at 2:45PM EDT by NWS Caribou ME",
        "severity": "Severe",
        "urgency": "Immediate",
        "effective": "2026-06-12T12:44:00-04:00",
        "expires": "2026-06-12T14:45:00-04:00",
        "areaDesc": "Aroostook, ME",
        "id": "urn:oid:2.49.0.1.840.0.a7541b53ce4c99c4079180b5a4a2bf8298ba4290.001.1",
        "source": "nws_alert"
      }
    ],
    "bank_robbery": [],
    "protest": [],
    "utility_outage": [],
    "transit_disruption": [],
    "wildfires": [],
    "transit": [],
    "amtrak": [],
    "aviation": [],
    "fema": [],
    "disease": []
  },
  "alert_count": 2,
  "date": "2026-06-12",
  "generated_at": "2026-06-12T17:47:49.970066+00:00"
}
