{
  "schema_version": "1.6",
  "fips": "25015",
  "name": "Hampshire County",
  "state": "MA",
  "centroid": {
    "lat": 42.339459,
    "lon": -72.663694
  },
  "alerts": {
    "weather": [
      {
        "event": "Extreme Heat Warning",
        "headline": "Extreme Heat Warning issued June 30 at 1:38AM EDT until July 4 at 8:00PM EDT by NWS Boston/Norton MA",
        "severity": "Severe",
        "urgency": "Expected",
        "effective": "2026-06-30T01:38:00-04:00",
        "expires": "2026-06-30T14:45:00-04:00",
        "areaDesc": "Hartford; Tolland; Windham; Eastern Franklin; Northern Worcester; Central Middlesex County; Western Essex; Eastern Essex; Eastern Hampshire; Eastern Hampden; Southern Worcester; Western Norfolk; Southeast Middlesex; Suffolk; Eastern Norfolk; Northern Bristol; Western Plymouth; Eastern Plymouth; Northwest Middlesex County; Northwest Providence; Southeast Providence; Western Kent; Eastern Kent",
        "id": "urn:oid:2.49.0.1.840.0.622c12c10014f0f9c68cce5486f36ab3935e557a.001.2",
        "source": "nws_alert"
      }
    ],
    "bank_robbery": [],
    "protest": [],
    "utility_outage": [],
    "transit_disruption": [],
    "wildfires": [],
    "transit": [],
    "amtrak": [],
    "aviation": [],
    "fema": [],
    "disease": []
  },
  "alert_count": 1,
  "date": "2026-06-30",
  "generated_at": "2026-06-30T10:45:28.275366+00:00"
}
