{
  "schema_version": "1.6",
  "fips": "26023",
  "name": "Branch County",
  "state": "MI",
  "centroid": {
    "lat": 41.918455,
    "lon": -85.066885
  },
  "alerts": {
    "weather": [
      {
        "event": "Heavy Precipitation Forecast",
        "headline": "~1.4\" rain expected in next 24h",
        "severity": "Moderate",
        "source": "nws_forecast"
      }
    ],
    "bank_robbery": [],
    "protest": [],
    "utility_outage": [],
    "transit_disruption": [],
    "wildfires": [],
    "transit": [],
    "amtrak": [],
    "aviation": [],
    "fema": [],
    "disease": []
  },
  "alert_count": 1,
  "date": "2026-06-17",
  "generated_at": "2026-06-17T12:13:20.246793+00:00"
}
