{
  "schema_version": "1.6",
  "fips": "32007",
  "name": "Elko County",
  "state": "NV",
  "centroid": {
    "lat": 41.141133,
    "lon": -115.351424
  },
  "alerts": {
    "weather": [
      {
        "event": "Freeze Warning",
        "headline": "Freeze Warning issued June 29 at 2:19AM PDT until June 29 at 8:00AM PDT by NWS Elko NV",
        "severity": "Severe",
        "urgency": "Expected",
        "effective": "2026-06-29T02:19:00-07:00",
        "expires": "2026-06-29T08:00:00-07:00",
        "areaDesc": "Northern Elko County; Ruby Mountains and East Humboldt Range; White Pine County; Southern Lander County and Southern Eureka County; Southwest Elko County; South Central Elko County",
        "id": "urn:oid:2.49.0.1.840.0.992b83a1c9c3974edd7040507182f65007c6d122.001.1",
        "source": "nws_alert"
      }
    ],
    "bank_robbery": [],
    "protest": [],
    "utility_outage": [],
    "transit_disruption": [],
    "wildfires": [],
    "transit": [],
    "amtrak": [],
    "aviation": [],
    "fema": [],
    "disease": []
  },
  "alert_count": 1,
  "date": "2026-06-29",
  "generated_at": "2026-06-29T12:16:22.145733+00:00"
}
