{
  "schema_version": "1.6",
  "fips": "39115",
  "name": "Morgan County",
  "state": "OH",
  "centroid": {
    "lat": 39.624946,
    "lon": -81.861697
  },
  "alerts": {
    "weather": [
      {
        "event": "Flash Flood Warning",
        "headline": "Flash Flood Warning issued June 18 at 6:43AM EDT until June 18 at 8:00AM EDT by NWS Charleston WV",
        "severity": "Severe",
        "urgency": "Immediate",
        "effective": "2026-06-18T06:43:00-04:00",
        "expires": "2026-06-18T08:00:00-04:00",
        "areaDesc": "Athens, OH; Morgan, OH; Washington, OH; Wood, WV",
        "id": "urn:oid:2.49.0.1.840.0.d8af91192b27d4088f0661d4eb6f51aae1e158cf.001.1",
        "source": "nws_alert"
      }
    ],
    "bank_robbery": [],
    "protest": [],
    "utility_outage": [],
    "transit_disruption": [],
    "wildfires": [],
    "transit": [],
    "amtrak": [],
    "aviation": [],
    "fema": [],
    "disease": []
  },
  "alert_count": 1,
  "date": "2026-06-18",
  "generated_at": "2026-06-18T11:40:39.574946+00:00"
}
