{
  "schema_version": "1.6",
  "fips": "41037",
  "name": "Lake County",
  "state": "OR",
  "centroid": {
    "lat": 42.788401,
    "lon": -120.38979
  },
  "alerts": {
    "weather": [
      {
        "event": "Red Flag Warning",
        "headline": "Red Flag Warning issued July 17 at 1:44AM PDT until July 17 at 8:00PM PDT by NWS Medford OR",
        "severity": "Severe",
        "urgency": "Expected",
        "effective": "2026-07-17T01:44:00-07:00",
        "expires": "2026-07-17T17:00:00-07:00",
        "areaDesc": "Modoc County Except for the Surprise Valley; Klamath Basin and the Fremont-Winema National Forest",
        "id": "urn:oid:2.49.0.1.840.0.bbdca340842545fc1039b5b2e0e428cbadf50372.002.1",
        "source": "nws_alert"
      }
    ],
    "bank_robbery": [],
    "protest": [],
    "utility_outage": [],
    "transit_disruption": [],
    "wildfires": [],
    "transit": [],
    "amtrak": [],
    "aviation": [],
    "fema": [],
    "disease": []
  },
  "alert_count": 1,
  "date": "2026-07-17",
  "generated_at": "2026-07-17T09:27:21.644656+00:00"
}
