{
  "schema_version": "1.6",
  "fips": "42073",
  "name": "Lawrence County",
  "state": "PA",
  "centroid": {
    "lat": 40.992735,
    "lon": -80.334446
  },
  "alerts": {
    "weather": [
      {
        "event": "Extreme Heat Warning",
        "headline": "Extreme Heat Warning issued July 2 at 2:16AM EDT until July 3 at 10:00PM EDT by NWS Pittsburgh PA",
        "severity": "Severe",
        "urgency": "Expected",
        "effective": "2026-07-02T02:16:00-04:00",
        "expires": "2026-07-02T14:00:00-04:00",
        "areaDesc": "Tuscarawas; Carroll; Columbiana; Coshocton; Harrison; Jefferson; Muskingum; Guernsey; Belmont; Noble; Monroe; Mercer; Venango; Forest; Lawrence; Butler; Clarion; Jefferson; Beaver; Allegheny; Armstrong; Washington; Greene; Westmoreland; Fayette; Indiana; Hancock; Brooke; Ohio; Marshall; Wetzel; Marion; Monongalia",
        "id": "urn:oid:2.49.0.1.840.0.18c6f85e5c626450898cbe0e4ca4298d011c49cf.001.1",
        "source": "nws_alert"
      }
    ],
    "bank_robbery": [],
    "protest": [],
    "utility_outage": [],
    "transit_disruption": [],
    "wildfires": [],
    "transit": [],
    "amtrak": [],
    "aviation": [],
    "fema": [],
    "disease": []
  },
  "alert_count": 1,
  "date": "2026-07-02",
  "generated_at": "2026-07-02T10:20:37.631581+00:00"
}
