{
  "schema_version": "1.6",
  "fips": "46103",
  "name": "Pennington County",
  "state": "SD",
  "centroid": {
    "lat": 44.002349,
    "lon": -102.823801
  },
  "alerts": {
    "weather": [],
    "bank_robbery": [],
    "protest": [],
    "utility_outage": [],
    "transit_disruption": [],
    "wildfires": [],
    "transit": [],
    "amtrak": [],
    "aviation": [],
    "fema": [],
    "disease": []
  },
  "alert_count": 0,
  "date": "2026-07-15",
  "generated_at": "2026-07-15T09:29:00.385960+00:00"
}
